{"trial_id": "09", "hyperparameters": {"space": [{"class_name": "Choice", "config": {"name": "lstm_units", "default": 64, "conditions": [], "values": [64, 128, 256], "ordered": true}}, {"class_name": "Choice", "config": {"name": "dropout", "default": 0.1, "conditions": [], "values": [0.1, 0.2, 0.3], "ordered": true}}, {"class_name": "Choice", "config": {"name": "learning_rate", "default": 0.0001, "conditions": [], "values": [0.0001, 0.001, 0.01], "ordered": true}}, {"class_name": "Choice", "config": {"name": "sequence_length", "default": 30, "conditions": [], "values": [30, 60, 90], "ordered": true}}, {"class_name": "Choice", "config": {"name": "batch_size", "default": 16, "conditions": [], "values": [16, 32, 64], "ordered": true}}], "values": {"lstm_units": 64, "dropout": 0.2, "learning_rate": 0.01, "sequence_length": 30, "batch_size": 64}}, "metrics": {"metrics": {"val_rmse": {"direction": "min", "observations": [{"value": [0.9916451871395111], "step": 0}]}}}, "score": 0.9916451871395111, "best_step": 0, "status": "COMPLETED", "message": null}